wborm/__init__.py
wborm/bootstrap.py
wborm/core.py
wborm/expressions.py
wborm/fields.py
wborm/introspect.py
wborm/model_cache.py
wborm/query.py
wborm/registry.py
wborm/utils.py
wborm/tests/__init__.py
wborm/tests/test_model.py
wborm-0.3.2.dist-info/licenses/LICENSE
wborm-0.3.2.dist-info/METADATA
wborm-0.3.2.dist-info/WHEEL
wborm-0.3.2.dist-info/top_level.txt
wborm-0.3.2.dist-info/RECORD
