Metadata-Version: 2.4
Name: wborm
Version: 0.3.2
Summary: ORM leve com introspecção automática para bancos JDBC como Informix, usando integração com wbjdbc.
Author-email: Wanderson Batista <wanderfreitasb@gmail.com>
License-Expression: MIT
Project-URL: Homepage, https://github.com/wanderbatistaf/wborm
Project-URL: Documentation, https://wanderbatistaf.github.io/wborm
Project-URL: Repository, https://github.com/wanderbatistaf/wborm
Keywords: ORM,JDBC,Informix,DB2,Firebird,introspecção,wbjdbc
Classifier: Development Status :: 4 - Beta
Classifier: Intended Audience :: Developers
Classifier: Programming Language :: Python :: 3
Classifier: Operating System :: OS Independent
Requires-Python: >=3.8
License-File: LICENSE
Requires-Dist: wbjdbc>=1.1.3
Requires-Dist: tabulate
Requires-Dist: termcolor
Requires-Dist: pandas; extra == "pandas"
Requires-Dist: pyspark; extra == "spark"
Dynamic: license-file
